snippet_image/__init__.py
snippet_image/image.py
snippet_image/size.py
snippet_image/text.py
snippet_image-0.1.7.dist-info/LICENSE
snippet_image-0.1.7.dist-info/WHEEL
snippet_image-0.1.7.dist-info/METADATA
snippet_image-0.1.7.dist-info/RECORD
