Metadata-Version: 2.1
Name: snippet-image
Version: 0.1.7
Summary: Package for simple creation images of snippets for social networks using pillow. Pictures for snippets can be inserted for sharing pages in social networks, for example in tag meta:
Home-page: https://github.com/acrius/snippet-image
License: MIT
Keywords: sharing,images,social,networks,snippets
Author: acrius
Author-email: acrius@mail.ru
Requires-Python: >=3.5,<4.0
Classifier: License :: OSI Approved :: MIT License
Classifier: Programming Language :: Python :: 3
Classifier: Programming Language :: Python :: 3.5
Classifier: Programming Language :: Python :: 3.6
Classifier: Programming Language :: Python :: 3.7
Requires-Dist: pillow (>=5.2,<7.0)
Project-URL: Repository, https://github.com/acrius/snippet-image
